kanu/__init__.py
kanu/__main__.py
kanu/chatgpt.py
kanu/chatpalm.py
kanu/constants.py
kanu/docgpt.py
kanu/funcgpt.py
kanu/gui.py
kanu/utils.py
kanu/version.py
kanu-0.9.0.dist-info/LICENSE
kanu-0.9.0.dist-info/METADATA
kanu-0.9.0.dist-info/WHEEL
kanu-0.9.0.dist-info/entry_points.txt
kanu-0.9.0.dist-info/top_level.txt
kanu-0.9.0.dist-info/RECORD
