Metadata-Version: 2.1
Name: kanu
Version: 0.9.0
Summary: A minimalistic Python-based GUI for various chatbots
Home-page: https://github.com/sbslee/kanu
Author: Seung-been "Steven" Lee
Author-email: sbstevenlee@gmail.com
License: MIT
Platform: UNKNOWN
License-File: LICENSE
